PyTimeVar/__init__.py
PyTimeVar/bhpfilter/__init__.py
PyTimeVar/bhpfilter/bHP.py
PyTimeVar/datasets/__init__.py
PyTimeVar/datasets/utils.py
PyTimeVar/datasets/co2/Emissions_19002017.csv
PyTimeVar/datasets/co2/__init__.py
PyTimeVar/datasets/co2/data.py
PyTimeVar/datasets/herding/CN HERDING.csv
PyTimeVar/datasets/herding/__init__.py
PyTimeVar/datasets/herding/data.py
PyTimeVar/datasets/inflation/CPIAUCSL.csv
PyTimeVar/datasets/inflation/__init__.py
PyTimeVar/datasets/inflation/data.py
PyTimeVar/datasets/temperature/__init__.py
PyTimeVar/datasets/temperature/data.py
PyTimeVar/datasets/temperature/temperature.csv
PyTimeVar/datasets/usd/USDindex.csv
PyTimeVar/datasets/usd/__init__.py
PyTimeVar/datasets/usd/data.py
PyTimeVar/gas/GAS.py
PyTimeVar/gas/__init__.py
PyTimeVar/kalman/__init__.py
PyTimeVar/kalman/kalman.py
PyTimeVar/locallinear/LLR.py
PyTimeVar/locallinear/__init__.py
PyTimeVar/powerlaw/__init__.py
PyTimeVar/powerlaw/pwr.py
PyTimeVar-1.0.0.dist-info/LICENSE.txt
PyTimeVar-1.0.0.dist-info/METADATA
PyTimeVar-1.0.0.dist-info/WHEEL
PyTimeVar-1.0.0.dist-info/top_level.txt
PyTimeVar-1.0.0.dist-info/RECORD
