Metadata-Version: 2.1
Name: PyTimeVar
Version: 1.0.0
Summary: The PyTimeVar package offers state-of-the-art estimation and statistical inference methods for time series regression models with flexible trends and/or time- varying coefficients.
Home-page: https://github.com/bpvand/PyTimeVar
Author: Mingxuan Song, Bernhard van der Sluis, Yicong Lin
Author-email: 678270ms@eur.nl, vandersluis@ese.eur.nl, yc.lin@vu.nl
License: GPLv3+
Keywords: time-varying,bootstrap,nonparametric estimation,filtering
Requires-Python: >=3.9
License-File: LICENSE.txt
Requires-Dist: numpy
Requires-Dist: pandas
Requires-Dist: matplotlib
Requires-Dist: scipy
Requires-Dist: statsmodels
Requires-Dist: tqdm
